{
    "parameters": {
        "location_x": "50%",
        "location_y": "50%",
        "width": 390,
        "height": 348
    },
    "items": [[
        [{"t": "column", "k": "column_1", "xx": true, "xy": true}, [
            [
                [{"t": "button", "k": "button_1", "v": "button_1", "s": [12, 6], "p":[[5, 5], [15, 5]]}],
                [{"t": "button", "k": "button_2", "v": "button_2", "s": [12, 6], "p":[[5, 5], [15, 5]]}],
                [{"t": "button", "k": "button_3", "v": "button_3", "s": [12, 6], "p":[[5, 5], [15, 5]]}]
            ],
            [
                [{"t": "button", "k": "button_4", "v": "button_4", "s": [12, 6], "p":[[5, 124], [5, 5]]}],
                [{"t": "button", "k": "button_5", "v": "button_5", "s": [12, 6]}]
            ],
            [
                [{"t": "button", "k": "button_6", "v": "button_6", "s": [12, 6]}],
                [{"t": "button", "k": "button_7", "v": "button_7", "s": [12, 6]}],
                [{"t": "button", "k": "button_8", "v": "button_8", "s": [12, 6]}]
            ]
        ]]
    ]]
}
